PyEnsembleCNN/__init__.py
PyEnsembleCNN/ensembles.py
PyEnsembleCNN-1.0.1.dist-info/METADATA
PyEnsembleCNN-1.0.1.dist-info/WHEEL
PyEnsembleCNN-1.0.1.dist-info/top_level.txt
PyEnsembleCNN-1.0.1.dist-info/RECORD
