Metadata-Version: 2.1
Name: PyEnsembleCNN
Version: 1.0.1
Summary: A dynamic CNN ensembling framework for PyTorch
Home-page: https://github.com/fostercm/PyEnsembleCNN
Author: Cole Foster
Author-email: colefoster2026@gmail.com
Classifier: Programming Language :: Python :: 3
Classifier: License :: OSI Approved :: MIT License
Classifier: Operating System :: OS Independent
Requires-Python: >=3.8
Requires-Dist: torch >=2.4.1
Requires-Dist: torchvision >=0.19.1
Requires-Dist: matplotlib >=3.7.5
Requires-Dist: grad-cam >=1.5.4
